pplate/__init__.py
pplate/main.py
pplate-0.1.1.dist-info/LICENSE
pplate-0.1.1.dist-info/METADATA
pplate-0.1.1.dist-info/WHEEL
pplate-0.1.1.dist-info/entry_points.txt
pplate-0.1.1.dist-info/RECORD
