Metadata-Version: 2.1
Name: pplate
Version: 0.1.1
Summary: A CLI to create, manage and use your own boilerplates
License: MIT
Author: hidekimsk
Author-email: Lucasmsk11@gmail.com
Requires-Python: >=3.8,<4.0
Classifier: License :: OSI Approved :: MIT License
Classifier: Programming Language :: Python :: 3
Classifier: Programming Language :: Python :: 3.8
Classifier: Programming Language :: Python :: 3.9
Classifier: Programming Language :: Python :: 3.10
Classifier: Programming Language :: Python :: 3.11
Classifier: Programming Language :: Python :: 3.12
Requires-Dist: typer (>=0.12.5,<0.13.0)
